slackperson.py
slackperson-0.5.1.dist-info/LICENSE
slackperson-0.5.1.dist-info/WHEEL
slackperson-0.5.1.dist-info/METADATA
slackperson-0.5.1.dist-info/RECORD
